LICENSE
MANIFEST.in
README.md
setup.cfg
setup.py
scikit_ExSTraCS.egg-info/PKG-INFO
scikit_ExSTraCS.egg-info/SOURCES.txt
scikit_ExSTraCS.egg-info/dependency_links.txt
scikit_ExSTraCS.egg-info/requires.txt
scikit_ExSTraCS.egg-info/top_level.txt
skExSTraCS/AttributeTracking.py
skExSTraCS/Classifier.py
skExSTraCS/ClassifierSet.py
skExSTraCS/DataManagement.py
skExSTraCS/ExSTraCS.py
skExSTraCS/ExpertKnowledge.py
skExSTraCS/IterationRecord.py
skExSTraCS/OfflineEnvironment.py
skExSTraCS/Prediction.py
skExSTraCS/RuleCompaction.py
skExSTraCS/StringEnumerator.py
skExSTraCS/Timer.py
skExSTraCS/__init__.py
test/.DS_Store
test/test_ExSTraCS.py
test/test_StringEnumerator.py
test/DataSets/Real/ContAndMissing.csv
test/DataSets/Real/ContinuousAndNonBinaryDiscreteAttributes.csv
test/DataSets/Real/ContinuousAndNonBinaryDiscreteAttributesMissing.csv
test/DataSets/Real/MulticlassPhenotype.csv
test/DataSets/Real/Multiplexer11.csv
test/DataSets/Real/Multiplexer11Modified.csv
test/DataSets/Real/Multiplexer20.csv
test/DataSets/Real/Multiplexer20Modified.csv
test/DataSets/Real/Multiplexer6.csv
test/DataSets/Real/Multiplexer6Modified.csv
test/DataSets/Tests/ContinuousPhenotype.csv
test/DataSets/Tests/MissingFeatureAndPhenotypeData.csv
test/DataSets/Tests/MissingFeatureData.csv
test/DataSets/Tests/StringData.csv
test/DataSets/Tests/StringData2.csv
test/DataSets/Tests/NumericTests/numericFloats.csv
test/DataSets/Tests/NumericTests/numericFloatsMissing.csv
test/DataSets/Tests/NumericTests/numericFloatsNAN.csv
test/DataSets/Tests/NumericTests/numericFloatsString.csv
test/DataSets/Tests/NumericTests/numericInts.csv
test/DataSets/Tests/SpecificityTests/Specifics.csv